plone.app.workflow-5.0.4-py3.13-nspkg.pth
plone/app/workflow/TODO.rst
plone/app/workflow/__init__.py
plone/app/workflow/configure.zcml
plone/app/workflow/events.py
plone/app/workflow/exportimport.py
plone/app/workflow/exportimport.zcml
plone/app/workflow/interfaces.py
plone/app/workflow/localroles.py
plone/app/workflow/permissions.py
plone/app/workflow/permissions.zcml
plone/app/workflow/remap.py
plone/app/workflow/testing.py
plone/app/workflow/browser/__init__.py
plone/app/workflow/browser/configure.zcml
plone/app/workflow/browser/macro_wrapper.pt
plone/app/workflow/browser/sharing.pt
plone/app/workflow/browser/sharing.py
plone/app/workflow/tests/__init__.py
plone/app/workflow/tests/onestateworkflow.rst
plone/app/workflow/tests/sharingpage.rst
plone/app/workflow/tests/test_exportimport.py
plone/app/workflow/tests/test_folder_workflow.py
plone/app/workflow/tests/test_functional.py
plone/app/workflow/tests/test_one_state_workflow.py
plone/app/workflow/tests/test_plone_workflow.py
plone/app/workflow/tests/test_remap.py
plone/app/workflow/tests/test_sharing_view.py
plone/app/workflow/tests/test_simple_publication_workflow.py
plone/app/workflow/tests/utils.py
plone.app.workflow-5.0.4.dist-info/METADATA
plone.app.workflow-5.0.4.dist-info/WHEEL
plone.app.workflow-5.0.4.dist-info/namespace_packages.txt
plone.app.workflow-5.0.4.dist-info/top_level.txt
plone.app.workflow-5.0.4.dist-info/RECORD
