Metadata-Version: 2.1
Name: plone.app.workflow
Version: 5.0.4
Summary: workflow and security settings for Plone
Home-page: https://github.com/plone/plone.app.workflow
Author: Plone Foundation
Author-email: plone-developers@lists.sourceforge.net
License: GPL version 2
Keywords: workflow sharing plone
Classifier: Development Status :: 5 - Production/Stable
Classifier: Environment :: Web Environment
Classifier: Framework :: Plone
Classifier: Framework :: Plone :: 6.0
Classifier: Framework :: Plone :: Core
Classifier: Framework :: Zope :: 5
Classifier: License :: OSI Approved :: GNU General Public License v2 (GPLv2)
Classifier: Operating System :: OS Independent
Classifier: Programming Language :: Python
Classifier: Programming Language :: Python :: 3.8
Classifier: Programming Language :: Python :: 3.9
Classifier: Programming Language :: Python :: 3.10
Classifier: Programming Language :: Python :: 3.11
Requires-Python: >=3.8
Requires-Dist: setuptools
Requires-Dist: persistent
Requires-Dist: plone.base
Requires-Dist: plone.i18n
Requires-Dist: plone.memoize
Requires-Dist: Products.statusmessages
Requires-Dist: Products.DCWorkflow
Requires-Dist: Products.GenericSetup
Requires-Dist: Zope
Provides-Extra: test
Requires-Dist: borg.localrole; extra == "test"
Requires-Dist: five.localsitemanager; extra == "test"
Requires-Dist: plone.app.testing; extra == "test"
Requires-Dist: plone.testing; extra == "test"
